msiwarp/__init__.py
msiwarp/msiwarp.cpython-38-darwin.so
msiwarp/util/__init__.py
msiwarp/util/parabolic_centroid.py
msiwarp/util/read_sbd.py
msiwarp/util/warp.py
msiwarp-0.1.dist-info/LICENSE
msiwarp-0.1.dist-info/METADATA
msiwarp-0.1.dist-info/WHEEL
msiwarp-0.1.dist-info/top_level.txt
msiwarp-0.1.dist-info/RECORD
